README.md
setup.py
xes/AIspeak.py
xes/__init__.py
xes/aiBase.py
xes/common.py
xes/data.py
xes/ext.py
xes/garbage.py
xes/library.py
xes/map.py
xes/provinces.py
xes/sms.py
xes/timesecret.py
xes/tool.py
xes/uploader.py
xes/version.py
xes/weather.py
xes/word.py
xes_lib_nopygame.egg-info/PKG-INFO
xes_lib_nopygame.egg-info/SOURCES.txt
xes_lib_nopygame.egg-info/dependency_links.txt
xes_lib_nopygame.egg-info/requires.txt
xes_lib_nopygame.egg-info/top_level.txt