Metadata-Version: 1.0
Name: xes-lib-nopygame
Version: 0.1.0
Summary: 学而思库
Home-page: https://code.xueersi.com
Author: xes
Author-email: UNKNOWN
License: UNKNOWN
Platform: UNKNOWN
